trethotapcode/__init__.py
trethotapcode/cat.py
trethotapcode/math.py
trethotapcode-1.0.0.dist-info/METADATA
trethotapcode-1.0.0.dist-info/WHEEL
trethotapcode-1.0.0.dist-info/RECORD
