Metadata-Version: 2.1
Name: trethotapcode
Version: 1.0.0
Summary: fix bug
Author: Your Name
Author-email: you@example.com
Requires-Python: >=3.12,<4.0
Classifier: Programming Language :: Python :: 3
Classifier: Programming Language :: Python :: 3.12
